posting/__init__.py
posting/__main__.py
posting/_start_time.py
posting/app.py
posting/auth.py
posting/collection.py
posting/commands.py
posting/config.py
posting/exit_codes.py
posting/files.py
posting/help_data.py
posting/help_screen.py
posting/highlight_url.py
posting/highlighters.py
posting/jump_overlay.py
posting/jumper.py
posting/locations.py
posting/messages.py
posting/posting.scss
posting/request_headers.py
posting/save_request.py
posting/scripts.py
posting/suggesters.py
posting/themes.py
posting/tuple_to_multidict.py
posting/types.py
posting/urls.py
posting/user_host.py
posting/variables.py
posting/version.py
posting/xresources.py
posting/yaml.py
posting/importing/curl.py
posting/importing/open_api.py
posting/importing/postman.py
posting/widgets/__init__.py
posting/widgets/center_middle.py
posting/widgets/confirmation.py
posting/widgets/datatable.py
posting/widgets/input.py
posting/widgets/key_value.py
posting/widgets/rich_log.py
posting/widgets/select.py
posting/widgets/tabbed_content.py
posting/widgets/text_area.py
posting/widgets/tree.py
posting/widgets/variable_autocomplete.py
posting/widgets/variable_input.py
posting/widgets/collection/browser.py
posting/widgets/collection/new_request_modal.py
posting/widgets/request/__init__.py
posting/widgets/request/form_editor.py
posting/widgets/request/header_editor.py
posting/widgets/request/method_selection.py
posting/widgets/request/path_editor.py
posting/widgets/request/query_editor.py
posting/widgets/request/request_auth.py
posting/widgets/request/request_body.py
posting/widgets/request/request_editor.py
posting/widgets/request/request_metadata.py
posting/widgets/request/request_options.py
posting/widgets/request/request_scripts.py
posting/widgets/request/url_bar.py
posting/widgets/response/cookies_table.py
posting/widgets/response/response_area.py
posting/widgets/response/response_body.py
posting/widgets/response/response_headers.py
posting/widgets/response/response_trace.py
posting-2.9.2.dist-info/METADATA
posting-2.9.2.dist-info/WHEEL
posting-2.9.2.dist-info/entry_points.txt
posting-2.9.2.dist-info/licenses/LICENSE
posting-2.9.2.dist-info/licenses/NOTICE
posting-2.9.2.dist-info/RECORD
