Metadata-Version: 2.4
Name: posting
Version: 2.9.2
Summary: The modern API client that lives in your terminal.
Project-URL: Homepage, https://github.com/darrenburns/posting
Project-URL: Repository, https://github.com/darrenburns/posting
Project-URL: Issues, https://github.com/darrenburns/posting/issues
Project-URL: Documentation, https://github.com/darrenburns/posting/blob/main/README.md
Author-email: Darren Burns <darrenb900@gmail.com>
License:                                  Apache License
License-File: LICENSE
License-File: NOTICE
Keywords: api,cli,client,developer-tool,http,posting,terminal,testing,textual,tui
Classifier: Development Status :: 5 - Production/Stable
Classifier: Environment :: Console
Classifier: Intended Audience :: Developers
Classifier: License :: OSI Approved :: Apache Software License
Classifier: Programming Language :: Python :: 3
Classifier: Programming Language :: Python :: 3.11
Classifier: Programming Language :: Python :: 3.12
Requires-Python: >=3.11
Requires-Dist: click-default-group<2.0.0,>=1.2.4
Requires-Dist: click<9.0.0,>=8.1.7
Requires-Dist: httpx[brotli]==0.28.1
Requires-Dist: openapi-pydantic>=0.5.0
Requires-Dist: pydantic-settings<3.0.0,>=2.4.0
Requires-Dist: pydantic<3.0.0,>=2.9.2
Requires-Dist: pyperclip<2.0.0,>=1.9.0
Requires-Dist: python-dotenv<2.0.0,>=1.0.1
Requires-Dist: pyyaml<7.0.0,>=6.0.2
Requires-Dist: textual-autocomplete==4.0.6
Requires-Dist: textual[syntax]==6.1.0
Requires-Dist: watchfiles>=0.24.0
Requires-Dist: xdg-base-dirs<7.0.0,>=6.0.1
